dashai_test_image_classification_plugin/__init__.py
dashai_test_image_classification_plugin/image_classification_model.py
dashai_test_image_classification_plugin/image_classification_task.py
dashai_test_image_classification_plugin/image_dataloader.py
dashai_test_image_classification_plugin/mlp_image_classifier.py
dashai_test_image_classification_plugin-0.0.7.dist-info/METADATA
dashai_test_image_classification_plugin-0.0.7.dist-info/WHEEL
dashai_test_image_classification_plugin-0.0.7.dist-info/entry_points.txt
dashai_test_image_classification_plugin-0.0.7.dist-info/RECORD
