Metadata-Version: 2.3
Name: dashai_test_image_classification_plugin
Version: 0.0.7
Summary: Image Classification Plugin for DashAI
Project-URL: Homepage, https://github.com/DashAISoftware/DashAI
Project-URL: Issues, https://github.com/DashAISoftware/DashAI/issues
Author: DashAI team
Author-email: dashaisoftware@gmail.com
Keywords: DashAI,Dataloader,Model,Task
Requires-Python: >=3.8
Requires-Dist: dashai-test-classification-metrics-plugin
Requires-Dist: torchvision==0.14.0
